hyprxa/__init__.py
hyprxa/__version__.py
hyprxa/_context.py
hyprxa/_exception_handlers.py
hyprxa/_exceptions.py
hyprxa/application.py
hyprxa/exceptions.py
hyprxa/py.typed
hyprxa/settings.py
hyprxa/types.py
hyprxa/auth/__init__.py
hyprxa/auth/base.py
hyprxa/auth/debug.py
hyprxa/auth/exceptions.py
hyprxa/auth/models.py
hyprxa/auth/protocols.py
hyprxa/auth/route.py
hyprxa/auth/scopes.py
hyprxa/base/__init__.py
hyprxa/base/exceptions.py
hyprxa/base/manager.py
hyprxa/base/models.py
hyprxa/base/subscriber.py
hyprxa/caching/__init__.py
hyprxa/caching/base.py
hyprxa/caching/core.py
hyprxa/caching/exceptions.py
hyprxa/caching/hashing.py
hyprxa/caching/memo.py
hyprxa/caching/singleton.py
hyprxa/client/__init__.py
hyprxa/client/base.py
hyprxa/client/client.py
hyprxa/dependencies/__init__.py
hyprxa/dependencies/auth.py
hyprxa/dependencies/db.py
hyprxa/dependencies/events.py
hyprxa/dependencies/info.py
hyprxa/dependencies/logs.py
hyprxa/dependencies/timeseries.py
hyprxa/dependencies/topics.py
hyprxa/dependencies/unitops.py
hyprxa/dependencies/util.py
hyprxa/events/__init__.py
hyprxa/events/exceptions.py
hyprxa/events/handler.py
hyprxa/events/manager.py
hyprxa/events/models.py
hyprxa/events/stream.py
hyprxa/events/subscriber.py
hyprxa/logging/__init__.py
hyprxa/logging/filters.py
hyprxa/logging/formatters.py
hyprxa/logging/handlers.py
hyprxa/logging/logging.yml
hyprxa/middleware/__init__.py
hyprxa/middleware/context.py
hyprxa/routes/__init__.py
hyprxa/routes/admin.py
hyprxa/routes/events.py
hyprxa/routes/timeseries.py
hyprxa/routes/topics.py
hyprxa/routes/unitops.py
hyprxa/routes/users.py
hyprxa/timeseries/__init__.py
hyprxa/timeseries/base.py
hyprxa/timeseries/exceptions.py
hyprxa/timeseries/handler.py
hyprxa/timeseries/lock.py
hyprxa/timeseries/manager.py
hyprxa/timeseries/models.py
hyprxa/timeseries/sources.py
hyprxa/timeseries/stream.py
hyprxa/timeseries/subscriber.py
hyprxa/timeseries/local/__init__.py
hyprxa/timeseries/local/chunks.py
hyprxa/timeseries/local/collection.py
hyprxa-0.0.6.dist-info/METADATA
hyprxa-0.0.6.dist-info/WHEEL
hyprxa-0.0.6.dist-info/licenses/LICENSE
hyprxa-0.0.6.dist-info/RECORD
