Metadata-Version: 2.1
Name: hyprxa
Version: 0.0.6
Summary: An asynchronous data integration framework and event hub built on FastAPI.
Project-URL: Changelog, https://github.com/newvicx/hyprxa/blob/master/CHANGELOG.md
Project-URL: Homepage, https://github.com/newvicx/hyprxa
Project-URL: Source, https://github.com/newvicx/hyprxa
Author-email: Chris Newville <chrisnewville1396@gmail.com>
License-Expression: MIT
License-File: LICENSE
Classifier: Development Status :: 3 - Alpha
Classifier: Environment :: Web Environment
Classifier: Framework :: AsyncIO
Classifier: Intended Audience :: Developers
Classifier: License :: OSI Approved :: MIT License
Classifier: Operating System :: OS Independent
Classifier: Programming Language :: Python :: 3
Classifier: Programming Language :: Python :: 3 :: Only
Classifier: Programming Language :: Python :: 3.10
Classifier: Programming Language :: Python :: 3.11
Requires-Python: >=3.10
Requires-Dist: accept-types
Requires-Dist: aiormq
Requires-Dist: asgi-correlation-id
Requires-Dist: fastapi
Requires-Dist: flatten-dict
Requires-Dist: httpx
Requires-Dist: httpx-auth
Requires-Dist: jsonlines
Requires-Dist: jsonschema
Requires-Dist: motor
Requires-Dist: ndjson
Requires-Dist: orjson
Requires-Dist: pendulum
Requires-Dist: pymemcache
Requires-Dist: python-jose
Requires-Dist: python-multipart
Requires-Dist: pyyaml
Requires-Dist: sentry-sdk
Requires-Dist: sse-starlette
Requires-Dist: toml
Requires-Dist: uvicorn[standard]
